{
  "title": "Daily ride 2024-03-05",
  "gpx": [
    "track.gpx"
  ],
  "date": "2024-03-05T00:00:00.000Z",
  "hash": [
    "6856a1232a509d1deb273a053a0b9f042bb023271583ab110d4fa3518b7ee6d"
  ],
  "objects": [],
  "tags": [],
  "time": 4297000,
  "distance": 17787.261977844173,
  "uphill": 79,
  "pointCount": 66,
  "tracks": [
    [
      {
        "lng": -121.98450905330355,
        "lat": 37.32429136346027,
        "tm": 1709672359000,
        "pathType": "line"
      },
      {
        "lng": -121.98813218687705,
        "lat": 37.32433124971074,
        "tm": 1709672423000,
        "pathType": "line"
      },
      {
        "lng": -121.99053054149988,
        "lat": 37.32322829520547,
        "tm": 1709672487000,
        "pathType": "line"
      },
      {
        "lng": -121.99231382248051,
        "lat": 37.322952623516706,
        "tm": 1709672551000,
        "pathType": "line"
      },
      {
        "lng": -121.99220168435866,
        "lat": 37.32335278319945,
        "tm": 1709672614000,
        "pathType": "line"
      }
    ],
    [
      {
        "lng": -121.99488218693432,
        "lat": 37.32321124180671,
        "tm": 1709673647000,
        "pathType": "line"
      },
      {
        "lng": -121.99824307402025,
        "lat": 37.32321555108823,
        "tm": 1709673777000,
        "pathType": "line"
      },
      {
        "lng": -122.00154812503031,
        "lat": 37.32314052473259,
        "tm": 1709673840000,
        "pathType": "line"
      },
      {
        "lng": -122.0055502986204,
        "lat": 37.32322599644716,
        "tm": 1709673904000,
        "pathType": "line"
      },
      {
        "lng": -122.00950285764867,
        "lat": 37.323098798754906,
        "tm": 1709673967000,
        "pathType": "line"
      },
      {
        "lng": -122.01320223093835,
        "lat": 37.32315405563401,
        "tm": 1709674032000,
        "pathType": "line"
      },
      {
        "lng": -122.01644529947178,
        "lat": 37.323076203062705,
        "tm": 1709674096000,
        "pathType": "line"
      },
      {
        "lng": -122.01856884371877,
        "lat": 37.32309986234708,
        "tm": 1709674159000,
        "pathType": "line"
      },
      {
        "lng": -122.02267607159358,
        "lat": 37.32308773873907,
        "tm": 1709674223000,
        "pathType": "line"
      },
      {
        "lng": -122.0271770068903,
        "lat": 37.32298095743139,
        "tm": 1709674286000,
        "pathType": "line"
      },
      {
        "lng": -122.02965341996159,
        "lat": 37.32308936365849,
        "tm": 1709674350000,
        "pathType": "line"
      },
      {
        "lng": -122.0339255535155,
        "lat": 37.322948170344965,
        "tm": 1709674414000,
        "pathType": "line"
      },
      {
        "lng": -122.03580841183793,
        "lat": 37.32302075164009,
        "tm": 1709674478000,
        "pathType": "line"
      },
      {
        "lng": -122.03974876508653,
        "lat": 37.32311002815635,
        "tm": 1709674541000,
        "pathType": "line"
      },
      {
        "lng": -122.04373299296606,
        "lat": 37.32303442606499,
        "tm": 1709674604000,
        "pathType": "line"
      },
      {
        "lng": -122.04591774975196,
        "lat": 37.32298854083189,
        "tm": 1709674671000,
        "pathType": "line"
      },
      {
        "lng": -122.04828596671268,
        "lat": 37.32298049273188,
        "tm": 1709674734000,
        "pathType": "line"
      },
      {
        "lng": -122.04922900253753,
        "lat": 37.322919899760095,
        "tm": 1709674799000,
        "pathType": "line"
      },
      {
        "lng": -122.05181347617832,
        "lat": 37.322951012572,
        "tm": 1709674863000,
        "pathType": "line"
      },
      {
        "lng": -122.05202841875835,
        "lat": 37.3226918195623,
        "tm": 1709674925000,
        "pathType": "line"
      },
      {
        "lng": -122.050390533264,
        "lat": 37.31961161804682,
        "tm": 1709674988000,
        "pathType": "line"
      },
      {
        "lng": -122.0497793835736,
        "lat": 37.316959261549236,
        "tm": 1709675051000,
        "pathType": "line"
      },
      {
        "lng": -122.05206062127128,
        "lat": 37.3172894548226,
        "tm": 1709675343000,
        "pathType": "line"
      }
    ],
    [
      {
        "lng": -122.05191126293099,
        "lat": 37.317198470874594,
        "tm": 1709694702000,
        "pathType": "line"
      },
      {
        "lng": -122.0494296825176,
        "lat": 37.317402277123264,
        "tm": 1709694765000,
        "pathType": "line"
      },
      {
        "lng": -122.05066182913626,
        "lat": 37.320704396689216,
        "tm": 1709694829000,
        "pathType": "line"
      },
      {
        "lng": -122.05084111810267,
        "lat": 37.32269024790748,
        "tm": 1709694893000,
        "pathType": "line"
      },
      {
        "lng": -122.04768290499489,
        "lat": 37.322696675075534,
        "tm": 1709694956000,
        "pathType": "line"
      },
      {
        "lng": -122.04235279389476,
        "lat": 37.32286969705082,
        "tm": 1709695020000,
        "pathType": "line"
      },
      {
        "lng": -122.04139832871033,
        "lat": 37.32402604485029,
        "tm": 1709695084000,
        "pathType": "line"
      },
      {
        "lng": -122.04139275061732,
        "lat": 37.32834892179391,
        "tm": 1709695147000,
        "pathType": "line"
      },
      {
        "lng": -122.04138927232067,
        "lat": 37.33287815709649,
        "tm": 1709695212000,
        "pathType": "line"
      },
      {
        "lng": -122.04131378741539,
        "lat": 37.33716764445161,
        "tm": 1709695275000,
        "pathType": "line"
      },
      {
        "lng": -122.03614670222798,
        "lat": 37.33745936166832,
        "tm": 1709695338000,
        "pathType": "line"
      },
      {
        "lng": -122.03021834803451,
        "lat": 37.337488495545514,
        "tm": 1709695402000,
        "pathType": "line"
      },
      {
        "lng": -122.02431737866937,
        "lat": 37.33758595695819,
        "tm": 1709695465000,
        "pathType": "line"
      },
      {
        "lng": -122.01869308830354,
        "lat": 37.337600728456536,
        "tm": 1709695528000,
        "pathType": "line"
      },
      {
        "lng": -122.01562670189573,
        "lat": 37.33763488491475,
        "tm": 1709695591000,
        "pathType": "line"
      },
      {
        "lng": -122.01241775671876,
        "lat": 37.33738576331562,
        "tm": 1709695654000,
        "pathType": "line"
      },
      {
        "lng": -122.00995775951698,
        "lat": 37.33693328054771,
        "tm": 1709695717000,
        "pathType": "line"
      },
      {
        "lng": -122.00762250928,
        "lat": 37.336665429822204,
        "tm": 1709695782000,
        "pathType": "line"
      }
    ],
    [
      {
        "lng": -122.00738564572944,
        "lat": 37.33660107216292,
        "tm": 1709696766000,
        "pathType": "line"
      },
      {
        "lng": -122.00798004381647,
        "lat": 37.336730104644666,
        "tm": 1709696891000,
        "pathType": "line"
      },
      {
        "lng": -122.01197428249527,
        "lat": 37.33684851947134,
        "tm": 1709696954000,
        "pathType": "line"
      },
      {
        "lng": -122.01226240010308,
        "lat": 37.33733493034404,
        "tm": 1709697019000,
        "pathType": "line"
      }
    ],
    [
      {
        "lng": -122.01256655566897,
        "lat": 37.337143996484784,
        "tm": 1709702491000,
        "pathType": "line"
      },
      {
        "lng": -122.01225463153247,
        "lat": 37.33743612877353,
        "tm": 1709702616000,
        "pathType": "line"
      },
      {
        "lng": -122.0076329083356,
        "lat": 37.337724416363905,
        "tm": 1709702680000,
        "pathType": "line"
      },
      {
        "lng": -122.00451529508902,
        "lat": 37.33768386246803,
        "tm": 1709702743000,
        "pathType": "line"
      },
      {
        "lng": -122.00027485288618,
        "lat": 37.33769012337005,
        "tm": 1709702807000,
        "pathType": "line"
      },
      {
        "lng": -121.99641169343388,
        "lat": 37.337713073911566,
        "tm": 1709702871000,
        "pathType": "line"
      },
      {
        "lng": -121.99589083855513,
        "lat": 37.33784993639754,
        "tm": 1709702933000,
        "pathType": "line"
      },
      {
        "lng": -121.9928283082488,
        "lat": 37.337678565416134,
        "tm": 1709702996000,
        "pathType": "line"
      },
      {
        "lng": -121.98866005674525,
        "lat": 37.33776596997998,
        "tm": 1709703060000,
        "pathType": "line"
      },
      {
        "lng": -121.98795068240557,
        "lat": 37.33565204108187,
        "tm": 1709703123000,
        "pathType": "line"
      },
      {
        "lng": -121.98919923977267,
        "lat": 37.33301038890972,
        "tm": 1709703187000,
        "pathType": "line"
      },
      {
        "lng": -121.9884682667701,
        "lat": 37.33098492974849,
        "tm": 1709703250000,
        "pathType": "line"
      },
      {
        "lng": -121.98624129673806,
        "lat": 37.329277844905086,
        "tm": 1709703314000,
        "pathType": "line"
      },
      {
        "lng": -121.98674755065696,
        "lat": 37.32655959549549,
        "tm": 1709703377000,
        "pathType": "line"
      },
      {
        "lng": -121.98621429326032,
        "lat": 37.324306585625465,
        "tm": 1709703441000,
        "pathType": "line"
      },
      {
        "lng": -121.98247128296744,
        "lat": 37.3242914733114,
        "tm": 1709703504000,
        "pathType": "line"
      }
    ]
  ]
}