{
  "title": "Daily ride 2022-11-19",
  "gpx": [
    "track.gpx"
  ],
  "date": "2022-11-19T00:00:00.000Z",
  "hash": [
    "fa65b4302340f68802870da9e909fa13dd5f2e751f240048d1afbb7553456ce4"
  ],
  "objects": [],
  "tags": [],
  "time": 6940000,
  "distance": 14827.360674111982,
  "uphill": 207,
  "pointCount": 79,
  "tracks": [
    [
      {
        "lng": -121.97905311246699,
        "lat": 37.32678739577947,
        "tm": 1668887474000,
        "pathType": "line"
      },
      {
        "lng": -121.97480523812754,
        "lat": 37.326744642547176,
        "tm": 1668887537000,
        "pathType": "line"
      },
      {
        "lng": -121.97381713747039,
        "lat": 37.329976134528565,
        "tm": 1668887601000,
        "pathType": "line"
      },
      {
        "lng": -121.96827610175013,
        "lat": 37.32987761664147,
        "tm": 1668887671000,
        "pathType": "line"
      },
      {
        "lng": -121.96452578131345,
        "lat": 37.32988615383691,
        "tm": 1668887734000,
        "pathType": "line"
      },
      {
        "lng": -121.96054319300474,
        "lat": 37.329840673110134,
        "tm": 1668887862000,
        "pathType": "line"
      },
      {
        "lng": -121.9570946920659,
        "lat": 37.32986780644024,
        "tm": 1668887926000,
        "pathType": "line"
      },
      {
        "lng": -121.95341314062654,
        "lat": 37.32989910256654,
        "tm": 1668887989000,
        "pathType": "line"
      },
      {
        "lng": -121.9503874135917,
        "lat": 37.32983601261385,
        "tm": 1668888053000,
        "pathType": "line"
      },
      {
        "lng": -121.95018037206184,
        "lat": 37.329916382148994,
        "tm": 1668888116000,
        "pathType": "line"
      },
      {
        "lng": -121.94529670570498,
        "lat": 37.33012335986781,
        "tm": 1668888180000,
        "pathType": "line"
      },
      {
        "lng": -121.942507140554,
        "lat": 37.33021898914405,
        "tm": 1668888243000,
        "pathType": "line"
      },
      {
        "lng": -121.93765598522398,
        "lat": 37.33011149232791,
        "tm": 1668888306000,
        "pathType": "line"
      },
      {
        "lng": -121.93445854239806,
        "lat": 37.33196131040689,
        "tm": 1668888370000,
        "pathType": "line"
      },
      {
        "lng": -121.93166888677054,
        "lat": 37.33409283148639,
        "tm": 1668888433000,
        "pathType": "line"
      },
      {
        "lng": -121.92822024112704,
        "lat": 37.336713344258804,
        "tm": 1668888498000,
        "pathType": "line"
      },
      {
        "lng": -121.92513466353661,
        "lat": 37.33485110897003,
        "tm": 1668888561000,
        "pathType": "line"
      },
      {
        "lng": -121.92361529626801,
        "lat": 37.334192347975645,
        "tm": 1668888625000,
        "pathType": "line"
      },
      {
        "lng": -121.92055499712389,
        "lat": 37.33661594541786,
        "tm": 1668888689000,
        "pathType": "line"
      },
      {
        "lng": -121.91942212261834,
        "lat": 37.3374526968782,
        "tm": 1668888752000,
        "pathType": "line"
      },
      {
        "lng": -121.91961184884306,
        "lat": 37.33765452132972,
        "tm": 1668888880000,
        "pathType": "line"
      },
      {
        "lng": -121.92016138012433,
        "lat": 37.337761622834826,
        "tm": 1668888952000,
        "pathType": "line"
      },
      {
        "lng": -121.91992335715311,
        "lat": 37.337795765765804,
        "tm": 1668889483000,
        "pathType": "line"
      },
      {
        "lng": -121.92005763906253,
        "lat": 37.337625989296534,
        "tm": 1668889958000,
        "pathType": "line"
      }
    ],
    [
      {
        "lng": -121.91991309215878,
        "lat": 37.337872563561554,
        "tm": 1668893220000,
        "pathType": "line"
      },
      {
        "lng": -121.92001512988796,
        "lat": 37.337710118852556,
        "tm": 1668893287000,
        "pathType": "line"
      },
      {
        "lng": -121.92161911173261,
        "lat": 37.33582815092592,
        "tm": 1668893674000,
        "pathType": "line"
      },
      {
        "lng": -121.92437195578583,
        "lat": 37.334255923151545,
        "tm": 1668893738000,
        "pathType": "line"
      },
      {
        "lng": -121.92677788963279,
        "lat": 37.33626428026502,
        "tm": 1668893803000,
        "pathType": "line"
      },
      {
        "lng": -121.92851096124222,
        "lat": 37.3367259121197,
        "tm": 1668893869000,
        "pathType": "line"
      },
      {
        "lng": -121.93116761577863,
        "lat": 37.33468188901712,
        "tm": 1668893934000,
        "pathType": "line"
      },
      {
        "lng": -121.9337493039422,
        "lat": 37.33266062072499,
        "tm": 1668893998000,
        "pathType": "line"
      },
      {
        "lng": -121.93453591689968,
        "lat": 37.3321137540403,
        "tm": 1668894064000,
        "pathType": "line"
      },
      {
        "lng": -121.93481887563078,
        "lat": 37.33208111509282,
        "tm": 1668894127000,
        "pathType": "line"
      },
      {
        "lng": -121.93976377934902,
        "lat": 37.33024437000364,
        "tm": 1668894193000,
        "pathType": "line"
      },
      {
        "lng": -121.94402663129567,
        "lat": 37.3302840540336,
        "tm": 1668894257000,
        "pathType": "line"
      },
      {
        "lng": -121.94754752249646,
        "lat": 37.330330861733394,
        "tm": 1668894321000,
        "pathType": "line"
      },
      {
        "lng": -121.9504417879809,
        "lat": 37.3300985183913,
        "tm": 1668894384000,
        "pathType": "line"
      },
      {
        "lng": -121.95435220821963,
        "lat": 37.33004741526472,
        "tm": 1668894448000,
        "pathType": "line"
      },
      {
        "lng": -121.95850971559031,
        "lat": 37.33002103681383,
        "tm": 1668894511000,
        "pathType": "line"
      },
      {
        "lng": -121.96282579550845,
        "lat": 37.330010884016204,
        "tm": 1668894575000,
        "pathType": "line"
      },
      {
        "lng": -121.96672583379203,
        "lat": 37.33006340904681,
        "tm": 1668894639000,
        "pathType": "line"
      },
      {
        "lng": -121.97061866590082,
        "lat": 37.33004567099464,
        "tm": 1668894705000,
        "pathType": "line"
      },
      {
        "lng": -121.97417653097793,
        "lat": 37.330237088486626,
        "tm": 1668894768000,
        "pathType": "line"
      },
      {
        "lng": -121.976548559324,
        "lat": 37.329979920279314,
        "tm": 1668894832000,
        "pathType": "line"
      },
      {
        "lng": -121.97905488350524,
        "lat": 37.3292980537751,
        "tm": 1668894897000,
        "pathType": "line"
      },
      {
        "lng": -121.97936122625975,
        "lat": 37.32682176906278,
        "tm": 1668894962000,
        "pathType": "line"
      }
    ],
    [
      {
        "lng": -121.9813505541898,
        "lat": 37.3244014359063,
        "tm": 1668902116000,
        "pathType": "line"
      },
      {
        "lng": -121.98200206731326,
        "lat": 37.3244628497648,
        "tm": 1668902180000,
        "pathType": "line"
      },
      {
        "lng": -121.98298660522956,
        "lat": 37.32442696691727,
        "tm": 1668902247000,
        "pathType": "line"
      },
      {
        "lng": -121.98371171464404,
        "lat": 37.32436664629842,
        "tm": 1668902311000,
        "pathType": "line"
      },
      {
        "lng": -121.9843927427167,
        "lat": 37.3243697192059,
        "tm": 1668902376000,
        "pathType": "line"
      },
      {
        "lng": -121.98505835799568,
        "lat": 37.324473775422625,
        "tm": 1668902440000,
        "pathType": "line"
      },
      {
        "lng": -121.98611165405109,
        "lat": 37.324447720922876,
        "tm": 1668902504000,
        "pathType": "line"
      },
      {
        "lng": -121.98715591975552,
        "lat": 37.32437064238033,
        "tm": 1668902569000,
        "pathType": "line"
      },
      {
        "lng": -121.98802909957995,
        "lat": 37.32440080472205,
        "tm": 1668902632000,
        "pathType": "line"
      },
      {
        "lng": -121.98892348050629,
        "lat": 37.32411988085117,
        "tm": 1668902695000,
        "pathType": "line"
      },
      {
        "lng": -121.98984797596985,
        "lat": 37.32410856062091,
        "tm": 1668902762000,
        "pathType": "line"
      },
      {
        "lng": -121.99044078015963,
        "lat": 37.32373412472193,
        "tm": 1668902825000,
        "pathType": "line"
      },
      {
        "lng": -121.99067640247821,
        "lat": 37.32323093929024,
        "tm": 1668902889000,
        "pathType": "line"
      },
      {
        "lng": -121.9917221202234,
        "lat": 37.3231952613099,
        "tm": 1668902953000,
        "pathType": "line"
      },
      {
        "lng": -121.99263613631766,
        "lat": 37.32327873360048,
        "tm": 1668903017000,
        "pathType": "line"
      },
      {
        "lng": -121.99274448288526,
        "lat": 37.32304764295618,
        "tm": 1668903213000,
        "pathType": "line"
      },
      {
        "lng": -121.99287964370538,
        "lat": 37.322818680377516,
        "tm": 1668903282000,
        "pathType": "line"
      },
      {
        "lng": -121.9931728291429,
        "lat": 37.32278222385637,
        "tm": 1668903683000,
        "pathType": "line"
      },
      {
        "lng": -121.99292433335556,
        "lat": 37.32275438776961,
        "tm": 1668903818000,
        "pathType": "line"
      }
    ],
    [
      {
        "lng": -121.99270575859106,
        "lat": 37.32300045732537,
        "tm": 1668904616000,
        "pathType": "line"
      },
      {
        "lng": -121.99068477355469,
        "lat": 37.32324658830987,
        "tm": 1668904869000,
        "pathType": "line"
      },
      {
        "lng": -121.98963476305391,
        "lat": 37.323223249201305,
        "tm": 1668904935000,
        "pathType": "line"
      },
      {
        "lng": -121.98874908927804,
        "lat": 37.323227719894476,
        "tm": 1668905001000,
        "pathType": "line"
      },
      {
        "lng": -121.98812204668756,
        "lat": 37.323268345926145,
        "tm": 1668905067000,
        "pathType": "line"
      },
      {
        "lng": -121.98785984813539,
        "lat": 37.32316139021582,
        "tm": 1668905133000,
        "pathType": "line"
      },
      {
        "lng": -121.98645018944858,
        "lat": 37.32322116939661,
        "tm": 1668905225000,
        "pathType": "line"
      },
      {
        "lng": -121.98578311137881,
        "lat": 37.323318706992424,
        "tm": 1668905292000,
        "pathType": "line"
      },
      {
        "lng": -121.98495412317341,
        "lat": 37.32328028652694,
        "tm": 1668905358000,
        "pathType": "line"
      },
      {
        "lng": -121.9838005325945,
        "lat": 37.32327940360827,
        "tm": 1668905424000,
        "pathType": "line"
      },
      {
        "lng": -121.98281934752643,
        "lat": 37.32324450038897,
        "tm": 1668905488000,
        "pathType": "line"
      },
      {
        "lng": -121.98253503733662,
        "lat": 37.32342572704722,
        "tm": 1668905551000,
        "pathType": "line"
      },
      {
        "lng": -121.9822835255922,
        "lat": 37.324260049607844,
        "tm": 1668905628000,
        "pathType": "line"
      }
    ]
  ]
}